tidegravity/__init__.py
tidegravity/tidegravity.py
tidegravity/trajectory_utils.py
tidegravity-0.5.0.dist-info/LICENSE
tidegravity-0.5.0.dist-info/METADATA
tidegravity-0.5.0.dist-info/WHEEL
tidegravity-0.5.0.dist-info/top_level.txt
tidegravity-0.5.0.dist-info/RECORD
