Metadata-Version: 2.1
Name: tidegravity
Version: 0.5.0
Summary: Tide gravitational correction based on I.M. Longman's Formulas for Computing the Tidal Accelerations Due to the Moon and the Sun
Home-page: https://github.com/bradyzp/LongmanTide/
Download-URL: https://github.com/bradyzp/LongmanTide
Author: Zachery P. Brady, John R. Leeman
Author-email: bradyzp@dynamicgravitysystems.com
Classifier: Development Status :: 4 - Beta
Classifier: Intended Audience :: Science/Research
Classifier: License :: OSI Approved :: MIT License
Classifier: Natural Language :: English
Classifier: Operating System :: Microsoft
Classifier: Operating System :: POSIX :: Linux
Classifier: Programming Language :: Python :: 3
Classifier: Programming Language :: Python :: Implementation :: CPython
Classifier: Topic :: Scientific/Engineering :: GIS
Classifier: Topic :: Scientific/Engineering :: Astronomy
Classifier: Topic :: Software Development :: Libraries
Requires-Python: >=3.5
License-File: LICENSE
Requires-Dist: numpy (==1.25.0)
Requires-Dist: pandas (==1.5.3)
Provides-Extra: mpl
Requires-Dist: matplotlib (>=2.2.0) ; extra == 'mpl'
